odoo/addons/l10n_ro_account_bank_statement_import_mt940_base/README.rst
odoo/addons/l10n_ro_account_bank_statement_import_mt940_base/__init__.py
odoo/addons/l10n_ro_account_bank_statement_import_mt940_base/__manifest__.py
odoo/addons/l10n_ro_account_bank_statement_import_mt940_base/i18n/l10n_ro_account_bank_statement_import_mt940_base.pot
odoo/addons/l10n_ro_account_bank_statement_import_mt940_base/i18n/ro.po
odoo/addons/l10n_ro_account_bank_statement_import_mt940_base/models/__init__.py
odoo/addons/l10n_ro_account_bank_statement_import_mt940_base/models/account_journal.py
odoo/addons/l10n_ro_account_bank_statement_import_mt940_base/models/res_bank.py
odoo/addons/l10n_ro_account_bank_statement_import_mt940_base/readme/CONTRIBUTORS.md
odoo/addons/l10n_ro_account_bank_statement_import_mt940_base/readme/DESCRIPTION.md
odoo/addons/l10n_ro_account_bank_statement_import_mt940_base/static/description/icon.png
odoo/addons/l10n_ro_account_bank_statement_import_mt940_base/static/description/icon.svg
odoo/addons/l10n_ro_account_bank_statement_import_mt940_base/static/description/index.html
odoo/addons/l10n_ro_account_bank_statement_import_mt940_base/test_files/test-rabo.swi
odoo/addons/l10n_ro_account_bank_statement_import_mt940_base/test_files/test-wrong-file.940
odoo/addons/l10n_ro_account_bank_statement_import_mt940_base/tests/__init__.py
odoo/addons/l10n_ro_account_bank_statement_import_mt940_base/tests/common.py
odoo/addons/l10n_ro_account_bank_statement_import_mt940_base/tests/test_import_bank_statement.py
odoo/addons/l10n_ro_account_bank_statement_import_mt940_base/views/res_bank_view.xml
odoo/addons/l10n_ro_account_bank_statement_import_mt940_base/wizard/__init__.py
odoo/addons/l10n_ro_account_bank_statement_import_mt940_base/wizard/account_bank_statement_import_mt940.py
odoo/addons/l10n_ro_account_bank_statement_import_mt940_base/wizard/mt940.py
odoo_addon_l10n_ro_account_bank_statement_import_mt940_base-19.0.0.4.0.dist-info/METADATA
odoo_addon_l10n_ro_account_bank_statement_import_mt940_base-19.0.0.4.0.dist-info/WHEEL
odoo_addon_l10n_ro_account_bank_statement_import_mt940_base-19.0.0.4.0.dist-info/top_level.txt
odoo_addon_l10n_ro_account_bank_statement_import_mt940_base-19.0.0.4.0.dist-info/RECORD
