Metadata-Version: 2.1
Name: odoo-addon-l10n_ro_account_bank_statement_import_mt940_base
Version: 19.0.0.4.0
Requires-Dist: odoo-addon-account_statement_import_file==19.0.*
Requires-Dist: odoo-addon-l10n_ro_config==19.0.*
Requires-Dist: odoo==19.0.*
Summary: Romania - MT940 Bank Statements Import
Home-page: https://github.com/OCA/l10n-romania
License: AGPL-3
Author: NextERP Romania,Odoo Community Association (OCA),Therp BV
Author-email: support@odoo-community.org
Classifier: Programming Language :: Python
Classifier: Framework :: Odoo
Classifier: Framework :: Odoo :: 19.0
Classifier: License :: OSI Approved :: GNU Affero General Public License v3
Classifier: Development Status :: 6 - Mature
